{
    "KPlugin": {
        "Authors": [
            {
                "Email": "me@venterum.com",
                "Name": "Venterum"
            }
        ],
        "Category": "System Information",
        "Description": "ChromeOS inspired Quick Settings Menu for KDE Plasma 6 made by Venterum",
        "Icon": "settings-app-symbolic",
        "Id": "com.venterum.quicksettings",
        "Name": "KDE QuickSettings",
        "Version": "Beta 0.9",
        "Website": "https://github.com/venterum/KDE-QuickSettings"
    },
    "KPackageStructure": "Plasma/Applet",
    "X-Plasma-API-Minimum-Version": "6.0"
} 